coralpay.py
coralpay_pkg/__init__.py
CoralPay-0.0.1.dist-info/LICENSE
CoralPay-0.0.1.dist-info/METADATA
CoralPay-0.0.1.dist-info/WHEEL
CoralPay-0.0.1.dist-info/top_level.txt
CoralPay-0.0.1.dist-info/RECORD
