Metadata-Version: 2.1
Name: CoralPay
Version: 0.0.1
Summary: CoralPay python libary
Home-page: https://github.com/beloved23/coralpay
Author: Adegoke Ayanfe
Author-email: adegokeayanfe@gmail.com
License: UNKNOWN
Platform: UNKNOWN
Classifier: Development Status :: 3 - Alpha
Classifier: Intended Audience :: Developers
Classifier: Topic :: Software Development :: Build Tools
Classifier: License :: OSI Approved :: MIT License
Classifier: Programming Language :: Python :: 3
Classifier: Programming Language :: Python :: 3.4
Classifier: Programming Language :: Python :: 3.5
Classifier: Programming Language :: Python :: 3.6
Requires-Python: >=3.6
Requires-Dist: pretty-bad-protocol
